sage/all__sagemath_environment.py
sage/env.py
sage/version.py
sage/features/__init__.py
sage/features/all.py
sage/features/bliss.py
sage/features/cddlib.py
sage/features/coxeter3.py
sage/features/csdp.py
sage/features/cython.py
sage/features/databases.py
sage/features/dot2tex.py
sage/features/dvipng.py
sage/features/ecm.py
sage/features/ffmpeg.py
sage/features/flatter.py
sage/features/four_ti_2.py
sage/features/fricas.py
sage/features/gap.py
sage/features/gfan.py
sage/features/giac.py
sage/features/graph_generators.py
sage/features/graphviz.py
sage/features/igraph.py
sage/features/imagemagick.py
sage/features/info.py
sage/features/interfaces.py
sage/features/internet.py
sage/features/jmol.py
sage/features/join_feature.py
sage/features/kenzo.py
sage/features/latex.py
sage/features/latte.py
sage/features/lrs.py
sage/features/mcqd.py
sage/features/meataxe.py
sage/features/meson_editable.py
sage/features/mip_backends.py
sage/features/msolve.py
sage/features/nauty.py
sage/features/normaliz.py
sage/features/palp.py
sage/features/pandoc.py
sage/features/pdf2svg.py
sage/features/phitigra.py
sage/features/pkg_systems.py
sage/features/polymake.py
sage/features/poppler.py
sage/features/rubiks.py
sage/features/sagemath.py
sage/features/sat.py
sage/features/singular.py
sage/features/sirocco.py
sage/features/sloane_database.py
sage/features/sphinx.py
sage/features/standard.py
sage/features/symengine_py.py
sage/features/tdlib.py
sage/features/threejs.py
sage/features/topcom.py
sage/misc/all__sagemath_environment.py
sage/misc/package.py
sage/misc/package_dir.py
sage/misc/temporary_file.py
sage/misc/viewer.py
sagemath_environment-10.7.data/scripts/sage
sagemath_environment-10.7.data/scripts/sage-env
sagemath_environment-10.7.data/scripts/sage-num-threads.py
sagemath_environment-10.7.data/scripts/sage-venv-config
sagemath_environment-10.7.data/scripts/sage-version.sh
sagemath_environment-10.7.dist-info/METADATA
sagemath_environment-10.7.dist-info/WHEEL
sagemath_environment-10.7.dist-info/top_level.txt
sagemath_environment-10.7.dist-info/RECORD
